MANIFEST.in
_version.py
setup.cfg
setup.py
tool/__init__.py
tool/application.py
tool/cli.py
tool/commands.py
tool/conf.py
tool/context_locals.py
tool/debug.py
tool/dist.py
tool/importing.py
tool/log.py
tool/plugins.py
tool/routing.py
tool/signals.py
tool.egg-info/PKG-INFO
tool.egg-info/SOURCES.txt
tool.egg-info/dependency_links.txt
tool.egg-info/requires.txt
tool.egg-info/top_level.txt
tool/ext/__init__.py
tool/ext/decorators.py
tool/ext/documents.py
tool/ext/http.py
tool/ext/pagination.py
tool/ext/shell.py
tool/ext/sqlobject_orm.py
tool/ext/storm_orm.py
tool/ext/strings.py
tool/ext/templating.py
tool/ext/werkzeug_routing.py
tool/ext/admin/__init__.py
tool/ext/admin/views.py
tool/ext/analysis/__init__.py
tool/ext/breadcrumbs/__init__.py
tool/ext/staticfiles/__init__.py
tool/ext/what/__init__.py
tool/ext/what/adapters.py
tool/ext/what/decorators.py
tool/ext/what/predicates.py
tool/ext/what/schema.py
tool/ext/who/__init__.py
tool/ext/who/decorators.py
tool/ext/who/forms.py
tool/ext/who/presets.py
tool/ext/who/schema.py
tool/ext/who/shortcuts.py
tool/ext/who/views.py
tool/ext/who/who_plugins.py